<?xml version="1.0" encoding="utf-8"?><resources>
    <package defaultValue="1" name="cn.jj"/>
    <package defaultValue="2" name="com.kiloo.subwaysurf"/>
    <package defaultValue="0" name="com.huawei.anyoffice"/>
    <package defaultValue="2" name="com.join.android.app.mgsim"/>
    <package defaultValue="2" name="com.brianbaek.popstar"/>
    <package defaultValue="2" name="com.diguayouxi"/>
    <package defaultValue="2" name="com.eg.android.AlipayGphone"/>
    <package defaultValue="0" name="com.huawei.bone"/>
    <package defaultValue="0" name="com.huawei.android.nfctag"/>
    <package defaultValue="2" name="com.ivali.qhbao"/>
    <package defaultValue="2" name="com.hexin.plat.android"/>
    <package defaultValue="2" name="com.ciyun.tiantianhongbao"/>
    <package defaultValue="2" name="com.qihoo.browser"/>
    <package defaultValue="2" name="org.funcity.runrunner.bdssb"/>
    <package defaultValue="2" name="com.m4399.gamecenter"/>
    <package defaultValue="2" name="com.huati"/>
    <package defaultValue="0" name="com.huawei.android.hwpay"/>
    <package defaultValue="2" name="com.tencent.qt.qtl"/>
    <package defaultValue="2" name="com.aspire.mm"/>
    <package defaultValue="2" name="com.taobao.appcenter"/>
    <package defaultValue="0" name="com.huawei.cloudwifi"/>
    <package defaultValue="2" name="com.huawei.eMobile"/>
    <package defaultValue="2" name="com.mojang.minecraftpe"/>
    <package defaultValue="0" name="com.huawei.android.airsharingcast"/>
    <package defaultValue="2" name="com.sogou.androidtool"/>
    <package defaultValue="0" name="com.huawei.skytone"/>
    <package defaultValue="2" name="com.qihoo.appstore"/>
    <package defaultValue="2" name="com.sohu.sohuvideo"/>
    <package defaultValue="0" name="com.huawei.fans"/>
    <package defaultValue="0" name="com.huawei.wallet"/>
    <package defaultValue="0" name="com.huawei.colorband"/>
    <package defaultValue="0" name="com.android.mediacenter"/>
    <package defaultValue="2" name="cn.egame.terminal.client4g"/>
    <package defaultValue="2" name="com.baidu.tieba"/>
    <package defaultValue="2" name="cn.goapk.market"/>
    <package defaultValue="2" name="com.xfplay.play"/>
    <package defaultValue="2" name="com.mycheering.apps"/>
    <package defaultValue="2" name="com.happy.lock"/>
    <package defaultValue="0" name="com.huawei.hiskytone"/>
    <package defaultValue="2" name="com.abifong.mfxssc"/>
    <package defaultValue="2" name="com.market2345"/>
    <package defaultValue="2" name="com.mycheering.launcher"/>
    <package defaultValue="0" name="com.huawei.remoteassistant"/>
    <package defaultValue="2" name="com.qianwang.qianbao"/>
    <package defaultValue="0" name="com.huawei.shine.camerarc"/>
    <package defaultValue="2" name="com.carrot.iceworld"/>
    <package defaultValue="0" name="com.huawei.phoneservice"/>
    <package defaultValue="1" name="com.baidu.video"/>
    <package defaultValue="0" name="com.hicloud.android.clone"/>
    <package defaultValue="2" name="me.mizhuan"/>
    <package defaultValue="2" name="wb.gc.xmxx.zxb"/>
    <package defaultValue="2" name="cn.ninegame.gamemanager"/>
    <package defaultValue="2" name="com.shuqi.controller"/>
    <package defaultValue="1" name="com.wuba"/>
    <package defaultValue="2" name="com.huawei.espacev2"/>
    <package defaultValue="2" name="com.pp.assistant"/>
    <package defaultValue="0" name="com.huawei.android.airsharingcastclient"/>
    <package defaultValue="2" name="com.dragon.android.pandaspace"/>
    <package defaultValue="2" name="com.le123.ysdq"/>
    <package defaultValue="2" name="com.huawei.it.ilearning.android"/>
    <package defaultValue="2" name="com.muzhiwan.market"/>
    <package defaultValue="0" name="com.huawei.health"/>
    <package defaultValue="0" name="com.huawei.appmarket"/>
    <package defaultValue="2" name="com.iflytek.inputmethod"/>
    <package defaultValue="2" name="com.huluxia.gametools"/>
    <package defaultValue="2" name="com.yingyonghui.market"/>
    <package defaultValue="1" name="com.happyelements.AndroidAnimal"/>
    <package defaultValue="2" name="com.icbc"/>
    <package defaultValue="2" name="com.app.pocketmoney"/>
    <package defaultValue="0" name="com.huawei.hisuite"/>
    <package defaultValue="2" name="com.huawei.onebox"/>
    <package defaultValue="0" name="com.huawei.gamebox"/>
    <package defaultValue="2" name="com.esbook.reader"/>
    <package defaultValue="2" name="com.duowan.groundhog.mctools"/>
    <package defaultValue="0" name="com.huawei.mytimeapp"/>
    <package defaultValue="0" name="huawei.w3"/>
    <package defaultValue="2" name="com.sogou.appmall"/>
    <package defaultValue="2" name="com.coohuaclient"/>
    <package defaultValue="2" name="com.huaqian"/>
    <package defaultValue="2" name="com.dewmobile.kuaiya"/>
    <package defaultValue="1" name="com.youloft.calendar"/>
    <package defaultValue="2" name="com.shoujiduoduo.ringtone"/>
    <package defaultValue="1" name="com.happyelements.AndroidAnimal.qq"/>
    <package defaultValue="2" name="com.hiapk.marketpho"/>
</resources>
